<?xml version="1.0" encoding="utf-8"?>
<resources xmlns:tools="http://schemas.android.com/tools" tools:ignore="MissingTranslation">
    <bool name="current_gtfs_rts_schedule_available">true</bool>
    <bool name="current_gtfs_rts_frequency_available">false</bool>
    <string name="current_gtfs_rts_area_min_lat">43.256679</string>
    <string name="current_gtfs_rts_area_max_lat">43.411717</string>
    <string name="current_gtfs_rts_area_min_lng">-79.892603</string>
    <string name="current_gtfs_rts_area_max_lng">-79.725184</string>
    <integer name="current_gtfs_rts_first_departure_in_sec">1705232100</integer><!-- 2024/01/14 06:35:00 EST -->
    <integer name="current_gtfs_rts_last_departure_in_sec">1708842600</integer><!-- 2024/02/25 01:30:00 EST -->
</resources>
